ssb_poetry/__init__.py
ssb_poetry-0.1.0.dist-info/METADATA
ssb_poetry-0.1.0.dist-info/WHEEL
ssb_poetry-0.1.0.dist-info/RECORD
