Metadata-Version: 2.1
Name: ssb-poetry
Version: 0.1.0
Summary: 
Author: Sergey
Author-email: sbshab1969@gmail.com
Requires-Python: >=3.12,<4.0
Classifier: Programming Language :: Python :: 3
Classifier: Programming Language :: Python :: 3.12
Requires-Dist: requests (>=2.32.3,<3.0.0)
